pdf_translation_api/__about__.py
pdf_translation_api/__init__.py
pdf_translation_api/gctranslate.py
pdf_translation_api-0.1.3.dist-info/METADATA
pdf_translation_api-0.1.3.dist-info/WHEEL
pdf_translation_api-0.1.3.dist-info/licenses/LICENSE.txt
pdf_translation_api-0.1.3.dist-info/RECORD
