Metadata-Version: 2.1
Name: pdf-translation-api
Version: 0.1.3
Summary: Utility to translate PDF files using Google Cloud Translate API
Project-URL: Documentation, https://github.com/abyesilyurt/pdf-translation-api#readme
Project-URL: Issues, https://github.com/abyesilyurt/pdf-translation-api/issues
Project-URL: Source, https://github.com/abyesilyurt/pdf-translation-api
Author-email: Aziz Berkay Yesilyurt <abyesilyurt@gmail.com>
License-Expression: MIT
License-File: LICENSE.txt
Keywords: api,cloud,google,pdf,translation
Classifier: Development Status :: 3 - Alpha
Classifier: Programming Language :: Python
Classifier: Programming Language :: Python :: 3.8
Classifier: Programming Language :: Python :: 3.9
Classifier: Programming Language :: Python :: 3.10
Classifier: Programming Language :: Python :: 3.11
Classifier: Programming Language :: Python :: 3.12
Classifier: Programming Language :: Python :: Implementation :: CPython
Classifier: Programming Language :: Python :: Implementation :: PyPy
Requires-Python: >=3.8
Requires-Dist: google-cloud-translate
